README.md
setup.py
themed_tkinter/__init__.py
themed_tkinter/abs_class.py
themed_tkinter/color.py
themed_tkinter/font.py
themed_tkinter/typing.py
themed_tkinter/util.py
themed_tkinter.egg-info/PKG-INFO
themed_tkinter.egg-info/SOURCES.txt
themed_tkinter.egg-info/dependency_links.txt
themed_tkinter.egg-info/top_level.txt
themed_tkinter/widget/__init__.py
themed_tkinter/widget/button.py
themed_tkinter/widget/entry.py
themed_tkinter/widget/frame.py
themed_tkinter/widget/label.py
themed_tkinter/widget/text.py
themed_tkinter/widget/tk.py
themed_tkinter/widget/top_level.py