Metadata-Version: 2.1
Name: themed-tkinter
Version: 0.0.3
Summary: Simple Friendly terminal interface
Home-page: https://gitlab.com/olive007/ufterm
Author: SECRET Olivier
Author-email: pypi-package-themed_tkinter@devo.live
License: UNKNOWN
Platform: UNKNOWN
Classifier: Programming Language :: Python :: 3
Classifier: License :: OSI Approved :: GNU Lesser General Public License v3 or later (LGPLv3+)
Classifier: Operating System :: OS Independent
